<v:view 
	xmlns="http://www.w3.org/1999/xhtml" 
	xmlns:v="http://www.cruxframework.org/view" 
	xmlns:core="http://www.cruxframework.org/crux" 
	xmlns:crux="http://www.cruxframework.org/crux/widgets"
	xmlns:gwt="http://www.cruxframework.org/crux/gwt"
	useController="mainController" title="Downloads"> 
	
	<div class="viewTextPanel">
		
		<h1>SAMPLE VIEW</h1>
		
		<p>Encontre aqui aplicações exemplo construídas com o Crux Framework. Aprenda gradativamente, lendo o código, executando as aplicações
		e modificando sua aparência e comportamento.</p>
		
		<center>
			<!-- div class="itemSlot appSlot sampleApp">
				<crux:button id="helloAppLabel" text="Hello World simples" onSelect="mainController.showViewExamples" styleName="infoButton"/>
			</div -->
		
			<div class="itemSlot appSlot sampleApp">
				<crux:button id="helloCrossAppLabel" text="Hello World multiplataforma" onSelect="mainController.showAppHelloCross" styleName="infoButton"/>
			</div>
			
			<div class="itemSlot appSlot sampleApp">
				<crux:button id="siteAppLabel" text="Site do Crux, feito com o Crux" onSelect="mainController.showAppSite" styleName="infoButton"/>
			</div>
			
			<div class="itemSlot appSlot sampleApp">
				<crux:button id="showcaseAppLabel" text="Showcase multiplataforma" onSelect="mainController.showAppShowcase" styleName="infoButton"/>
			</div>
		</center>
	</div>
	
</v:view>